topsis/__init__.py
topsis/topsis.py
102203236_Topsis-0.0.1.dist-info/LICENSE.txt
102203236_Topsis-0.0.1.dist-info/METADATA
102203236_Topsis-0.0.1.dist-info/WHEEL
102203236_Topsis-0.0.1.dist-info/top_level.txt
102203236_Topsis-0.0.1.dist-info/RECORD
